aspose/__init__.py
aspose/finance.cp310-win_amd64.pyd
aspose/finance.cp311-win_amd64.pyd
aspose/finance.cp35-win_amd64.pyd
aspose/finance.cp36-win_amd64.pyd
aspose/finance.cp37-win_amd64.pyd
aspose/finance.cp38-win_amd64.pyd
aspose/finance.cp39-win_amd64.pyd
aspose/pycore.cp310-win_amd64.pyd
aspose/pycore.cp311-win_amd64.pyd
aspose/pycore.cp35-win_amd64.pyd
aspose/pycore.cp36-win_amd64.pyd
aspose/pycore.cp37-win_amd64.pyd
aspose/pycore.cp38-win_amd64.pyd
aspose/pycore.cp39-win_amd64.pyd
aspose/pygc.cp310-win_amd64.pyd
aspose/pygc.cp311-win_amd64.pyd
aspose/pygc.cp35-win_amd64.pyd
aspose/pygc.cp36-win_amd64.pyd
aspose/pygc.cp37-win_amd64.pyd
aspose/pygc.cp38-win_amd64.pyd
aspose/pygc.cp39-win_amd64.pyd
aspose/pyreflection.cp310-win_amd64.pyd
aspose/pyreflection.cp311-win_amd64.pyd
aspose/pyreflection.cp35-win_amd64.pyd
aspose/pyreflection.cp36-win_amd64.pyd
aspose/pyreflection.cp37-win_amd64.pyd
aspose/pyreflection.cp38-win_amd64.pyd
aspose/pyreflection.cp39-win_amd64.pyd
aspose/__pyinstaller/__init__.pyi
aspose/__pyinstaller/hook-aspose.py
aspose/assemblies/finance/Aspose.Finance.dll
aspose/assemblies/finance/Microsoft.Win32.SystemEvents.dll
aspose/assemblies/finance/System.Drawing.Common.dll
aspose/assemblies/finance/WrpInterop.Aspose.Finance.dll
aspose/assemblies/pycore/WrpInterop.Aspose.PyCore.dll
aspose/assemblies/pygc/Aspose.PyGC.dll
aspose/assemblies/pyreflection/WrpInterop.Aspose.PyReflection.dll
aspose/finance/__init__.pyi
aspose/finance/__pyinstaller/__init__.pyi
aspose/finance/__pyinstaller/hook-aspose.finance.py
aspose/netcore/netcore3.1/Microsoft.CSharp.dll
aspose/netcore/netcore3.1/Microsoft.DiaSymReader.Native.amd64.dll
aspose/netcore/netcore3.1/Microsoft.VisualBasic.Core.dll
aspose/netcore/netcore3.1/Microsoft.VisualBasic.dll
aspose/netcore/netcore3.1/Microsoft.Win32.Primitives.dll
aspose/netcore/netcore3.1/Microsoft.Win32.Registry.dll
aspose/netcore/netcore3.1/SOS_README.md
aspose/netcore/netcore3.1/System.AppContext.dll
aspose_finance-25.3.dist-info/METADATA
aspose_finance-25.3.dist-info/WHEEL
aspose_finance-25.3.dist-info/entry_points.txt
aspose_finance-25.3.dist-info/top_level.txt
aspose_finance-25.3.dist-info/RECORD
