Metadata-Version: 2.1
Name: aspose-finance
Version: 25.3
Summary: Aspose.Finance for Python via .NET  is a scalable and feature-rich API to process finance-related formats, such as, XBRL iXBRL and OFX, using Python. API offers XBRL,iXBRL,OFX file creation, manipulation and conversion.
Home-page: https://products.aspose.com/finance/
Author: aspose-finance
License: https://company.aspose.com/legal/eula
Keywords: xbrl,ixbrl,ofx,finance,conversion
Platform: win_amd64
Classifier: Intended Audience :: Developers
Classifier: Intended Audience :: Education
Classifier: Intended Audience :: Manufacturing
Classifier: Intended Audience :: Science/Research
Classifier: Operating System :: Microsoft :: Windows
Classifier: Operating System :: POSIX :: Linux
Classifier: Operating System :: Unix
Classifier: License :: Free To Use But Restricted
Classifier: License :: Other/Proprietary License
Classifier: Programming Language :: Python :: 3
Classifier: Programming Language :: Python :: 3 :: Only
Classifier: Programming Language :: Python :: 3.5
Classifier: Programming Language :: Python :: 3.6
Classifier: Programming Language :: Python :: 3.7
Classifier: Programming Language :: Python :: 3.8
Classifier: Programming Language :: Python :: 3.9
Classifier: Programming Language :: Python :: 3.10
Classifier: Topic :: Software Development :: Libraries
Classifier: Topic :: Multimedia :: Graphics :: Graphics Conversion
Requires-Python: >=3.5,<3.12
